imstr.py
imstr-0.0.16.dist-info/LICENSE
imstr-0.0.16.dist-info/METADATA
imstr-0.0.16.dist-info/WHEEL
imstr-0.0.16.dist-info/entry_points.txt
imstr-0.0.16.dist-info/top_level.txt
imstr-0.0.16.dist-info/RECORD
