Metadata-Version: 2.1
Name: imstr
Version: 0.0.16
Summary: A command line tool for converting images to strings
Author: Harry Downing
Author-email: harry.downing17@gmail.com
Project-URL: repository, https://github.com/harrydowning/imstr
Classifier: Programming Language :: Python :: 3
Classifier: License :: OSI Approved :: MIT License
Classifier: Operating System :: OS Independent
Requires-Python: >=3.6
License-File: LICENSE
Requires-Dist: opencv-python
Requires-Dist: docopt
